{
	"$schema": "http://schema.management.azure.com/schemas/2015-01-01/deploymentTemplate.json#",
	"contentVersion": "1.0.0.0",
	"parameters": {
		"factoryName": {
			"type": "string",
			"metadata": "Data Factory name",
			"defaultValue": "adf-faisal-demo-01"
		},
		"AzureBlobStorage1_connectionString": {
			"type": "secureString",
			"metadata": "Secure string for 'connectionString' of 'AzureBlobStorage1'"
		},
		"AzureDataLakeStorage1_accountKey": {
			"type": "secureString",
			"metadata": "Secure string for 'accountKey' of 'AzureDataLakeStorage1'"
		},
		"AzureDataLakeStorage2_accountKey": {
			"type": "secureString",
			"metadata": "Secure string for 'accountKey' of 'AzureDataLakeStorage2'"
		},
		"AzureDataLakeStorage1_properties_typeProperties_url": {
			"type": "string",
			"defaultValue": "https://faisaldatalakegen2.dfs.core.windows.net/"
		},
		"AzureDataLakeStorage2_properties_typeProperties_url": {
			"type": "string",
			"defaultValue": "https://faisaldatalakegen2.dfs.core.windows.net/"
		},
		"RestService1_properties_typeProperties_url": {
			"type": "string",
			"defaultValue": "https://api.onegov.nsw.gov.au/ "
		}
	},
	"variables": {
		"factoryId": "[concat('Microsoft.DataFactory/factories/', parameters('factoryName'))]"
	},
	"resources": [
		{
			"name": "[concat(parameters('factoryName'), '/pipeline1')]",
			"type": "Microsoft.DataFactory/factories/pipelines",
			"apiVersion": "2018-06-01",
			"properties": {
				"activities": [
					{
						"name": "ReadRestAPI",
						"type": "WebActivity",
						"dependsOn": [],
						"policy": {
							"timeout": "0.12:00:00",
							"retry": 0,
							"retryIntervalInSeconds": 30,
							"secureOutput": false,
							"secureInput": false
						},
						"userProperties": [],
						"typeProperties": {
							"url": "https://dummy.restapiexample.com/api/v1/employees",
							"method": "GET",
							"headers": {}
						}
					},
					{
						"name": "SaveOutputinBlob",
						"type": "WebActivity",
						"dependsOn": [
							{
								"activity": "ReadRestAPI",
								"dependencyConditions": [
									"Succeeded"
								]
							}
						],
						"policy": {
							"timeout": "0.12:00:00",
							"retry": 0,
							"retryIntervalInSeconds": 30,
							"secureOutput": false,
							"secureInput": false
						},
						"userProperties": [],
						"typeProperties": {
							"url": "https://faisaldatalakegen2.blob.core.windows.net/green?sp=racw&st=2023-10-01T01:56:55Z&se=2023-10-01T09:56:55Z&spr=https&sv=2022-11-02&sr=c&sig=BY809%2BHGMDshMLLPcyg55184QTEOe1R6i2%2F8U316D14%3D",
							"method": "POST",
							"headers": {
								"x-ms-blob-type": "BlockBlob"
							},
							"body": {
								"value": "@activity('ReadRestAPI').output",
								"type": "Expression"
							}
						}
					}
				],
				"policy": {
					"elapsedTimeMetric": {}
				},
				"annotations": []
			},
			"dependsOn": []
		},
		{
			"name": "[concat(parameters('factoryName'), '/AzureBlobStorage1')]",
			"type": "Microsoft.DataFactory/factories/linkedServices",
			"apiVersion": "2018-06-01",
			"properties": {
				"annotations": [],
				"type": "AzureBlobStorage",
				"typeProperties": {
					"connectionString": "[parameters('AzureBlobStorage1_connectionString')]"
				}
			},
			"dependsOn": []
		},
		{
			"name": "[concat(parameters('factoryName'), '/AzureDataLakeStorage1')]",
			"type": "Microsoft.DataFactory/factories/linkedServices",
			"apiVersion": "2018-06-01",
			"properties": {
				"annotations": [],
				"type": "AzureBlobFS",
				"typeProperties": {
					"url": "[parameters('AzureDataLakeStorage1_properties_typeProperties_url')]",
					"accountKey": {
						"type": "SecureString",
						"value": "[parameters('AzureDataLakeStorage1_accountKey')]"
					}
				}
			},
			"dependsOn": []
		},
		{
			"name": "[concat(parameters('factoryName'), '/AzureDataLakeStorage2')]",
			"type": "Microsoft.DataFactory/factories/linkedServices",
			"apiVersion": "2018-06-01",
			"properties": {
				"annotations": [],
				"type": "AzureBlobFS",
				"typeProperties": {
					"url": "[parameters('AzureDataLakeStorage2_properties_typeProperties_url')]",
					"accountKey": {
						"type": "SecureString",
						"value": "[parameters('AzureDataLakeStorage2_accountKey')]"
					}
				}
			},
			"dependsOn": []
		},
		{
			"name": "[concat(parameters('factoryName'), '/RestService1')]",
			"type": "Microsoft.DataFactory/factories/linkedServices",
			"apiVersion": "2018-06-01",
			"properties": {
				"annotations": [],
				"type": "RestService",
				"typeProperties": {
					"url": "[parameters('RestService1_properties_typeProperties_url')]",
					"enableServerCertificateValidation": true,
					"authenticationType": "Anonymous"
				}
			},
			"dependsOn": []
		}
	]
}